elasticsearch_pydantic/__init__.py
elasticsearch_pydantic/_base.py
elasticsearch_pydantic/_compat.py
elasticsearch_pydantic/_fields.py
elasticsearch_pydantic/test_mapping.py
elasticsearch_pydantic/test_serialization.py
elasticsearch_pydantic/test_validation.py
elasticsearch_pydantic-1.1.dist-info/licenses/LICENSE
elasticsearch_pydantic-1.1.dist-info/METADATA
elasticsearch_pydantic-1.1.dist-info/WHEEL
elasticsearch_pydantic-1.1.dist-info/top_level.txt
elasticsearch_pydantic-1.1.dist-info/RECORD
