Metadata-Version: 2.4
Name: elasticsearch-pydantic
Version: 1.1
Summary: Use the Elasticsearch DSL with Pydantic models.
Author-email: Jan Heinrich Merker <heinrich.merker@uni-jena.de>
License-Expression: MIT
Project-URL: Homepage, https://github.com/janheinrichmerker/elasticsearch-pydantic
Project-URL: Bug Tracker, https://github.com/janheinrichmerker/elasticsearch-pydantic/issues
Classifier: Programming Language :: Python :: 3
Classifier: Programming Language :: Python :: 3 :: Only
Classifier: Programming Language :: Python :: 3.11
Classifier: Programming Language :: Python :: 3.12
Classifier: Programming Language :: Python :: 3.13
Classifier: Operating System :: OS Independent
Classifier: Intended Audience :: Science/Research
Classifier: Topic :: Scientific/Engineering
Requires-Python: >=3.11
License-File: LICENSE
Requires-Dist: annotated-types~=0.7.0
Requires-Dist: elastic-transport~=8.0
Requires-Dist: pydantic~=2.11
Provides-Extra: tests
Requires-Dist: mypy~=1.6; extra == "tests"
Requires-Dist: pydantic[email]~=2.11; extra == "tests"
Requires-Dist: pytest~=8.0; extra == "tests"
Requires-Dist: pytest-cov<8.0,>=6.3; extra == "tests"
Requires-Dist: ruff~=0.9; extra == "tests"
Provides-Extra: tests-es6
Requires-Dist: elasticsearch-dsl~=6.0; extra == "tests-es6"
Provides-Extra: tests-es6-major
Requires-Dist: elasticsearch6-dsl~=6.0; extra == "tests-es6-major"
Provides-Extra: tests-es7
Requires-Dist: elasticsearch-dsl~=7.0; extra == "tests-es7"
Provides-Extra: tests-es7-major
Requires-Dist: elasticsearch7-dsl~=7.0; extra == "tests-es7-major"
Provides-Extra: tests-es8
Requires-Dist: elasticsearch-dsl~=8.11.0; extra == "tests-es8"
Provides-Extra: tests-es8-major
Requires-Dist: elasticsearch8-dsl~=8.11.0; extra == "tests-es8-major"
Dynamic: license-file
